PSM_testbed/__init__.py
PSM_testbed/WhACC/__init__.py
PSM_testbed/WhACC/image_tools.py
PSM_testbed/WhACC/pole_tracker.py
PSM_testbed/WhACC/subset_H5_generator_old.py
PSM_testbed/WhACC/subset_h5_for_retraining.py
PSM_testbed/WhACC/subset_h5_generator.py
PSM_testbed/WhACC/touch_curation_GUI.py
PSM_testbed/WhACC/utils.py
PSM_testbed/WhACC/whacc_utilities.py
PSM_testbed/WhACC/examples/__init__.py
PSM_testbed/WhACC/examples/add_pole_times.py
PSM_testbed/WhACC/examples/gui_example.py
PSM_testbed/WhACC/examples/h5_tester.py
PSM_testbed/WhACC/examples/make_h5_example.py
PSM_testbed/WhACC/examples/make_subset_H5_example.py
PSM_testbed/WhACC/examples/predict_touches_example.py
PSM_testbed-0.0.0.26.dist-info/METADATA
PSM_testbed-0.0.0.26.dist-info/WHEEL
PSM_testbed-0.0.0.26.dist-info/top_level.txt
PSM_testbed-0.0.0.26.dist-info/RECORD
