Metadata-Version: 2.1
Name: PSM-testbed
Version: 0.0.0.26
Summary: A testbed package for Phillip Maire
Home-page: UNKNOWN
Author: UNKNOWN
Author-email: phillip.maire@gmail.com
License: UNKNOWN
Platform: UNKNOWN
Requires-Dist: natsort (==7.1.1)
